pointing_utils/__init__.py
pointing_utils/utils.py
pointing_utils-0.0.1.dist-info/LICENSE
pointing_utils-0.0.1.dist-info/WHEEL
pointing_utils-0.0.1.dist-info/METADATA
pointing_utils-0.0.1.dist-info/RECORD
