Metadata-Version: 2.1
Name: pointing-utils
Version: 0.0.1
Summary: Utilities for dealing with pointing data
Author: jgori
Author-email: juliengori@gmail.com
Requires-Python: >=3.8,<3.11
Classifier: Programming Language :: Python :: 3
Classifier: Programming Language :: Python :: 3.10
Classifier: Programming Language :: Python :: 3.8
Classifier: Programming Language :: Python :: 3.9
Requires-Dist: emgregs (>=0.0.4,<0.0.5)
Requires-Dist: matplotlib (>=3.7.0,<4.0.0)
Requires-Dist: numpy (>=1.24.2,<2.0.0)
Requires-Dist: pandas (>=1.5.3,<2.0.0)
Requires-Dist: statsmodels (>=0.13.5,<0.14.0)
